alpha_cli/__init__.py
alpha_cli/credentials.py
alpha_cli/main.py
alpha_cli/output.py
alpha_cli/types.py
alpha_cli/clients/__init__.py
alpha_cli/clients/congress.py
alpha_cli/clients/kalshi.py
alpha_cli/commands/__init__.py
alpha_cli/commands/config.py
alpha_cli/commands/congress.py
alpha_cli/commands/kalshi.py
alpha_cli/commands/scan.py
alpha_cli/services/__init__.py
alpha_cli/services/matching.py
alpha_cli/services/scan.py
alpha_cli/utils/__init__.py
alpha_cli/utils/cache.py
alpha_cli/utils/circuit_breaker.py
alpha_cli/utils/retry.py
alpha_cli-0.1.0.dist-info/METADATA
alpha_cli-0.1.0.dist-info/WHEEL
alpha_cli-0.1.0.dist-info/entry_points.txt
alpha_cli-0.1.0.dist-info/RECORD
